{
  "pageName": {
    "table": "查看预约",
    "new": "添加账号",
    "edit": "编辑账号"
  },
  "listAPI": "/api/crud/oms/wispInstance/wispInstances",
  "createAPI": "/api/crud/oms/wispInstance/wispInstances",
  "getAPI": "/api/crud/oms/wispInstance/wispInstances/[id]",
  "updateAPI": "/api/crud/oms/wispInstance/wispInstances/[id]",
  "deleteAPI": "/api/crud/oms/wispInstance/wispInstances/(id)",
  "columns": 1,
  "createFields": [
  ],
  "updateFields": [
  ],
  "map": {},
  "layout": {
    "table": "Content",
    "form": "TitleContent"
  },
  "tableActions": [
  ],
  "tableOperation": [
  ],
  "searchFields": [
  ],
  "tableFields": [{
      "label": "序号",
      "field": "id",
      "align":"center"
    },
    {
      "label": "玩家",
      "field": "name",
      "align":"center"
    },
    {
      "label": "预约精灵",
      "field": "sortorder",
      "align":"center"
    },
    {
      "label": "预约场次",
      "field": "note",
      "align":"center"
    },
    {
      "label": "购买的精灵",
      "field": "note",
      "align":"center"
    },
    {
      "label": "租用的土地",
      "field": "note",
      "align":"center"
    },
    {
      "label": "预约时间",
      "field": "note",
      "align":"center"
    }
  ],
  "viewConfig": []
}
